{
  "videos": [],
  "category": [],
  "history": [
 
    {
      "id": "lsypivw8",
      "cardname": "Kuthanthram - Manjummel Boys Promo Song ",
      "url": "https://www.youtube.com/embed/9AizchSQURA",
      "date": "02/23/2024,7:17:52 PM"
    },
    {
      "id": "lsyq52mr",
      "cardname": "Kuthanthram - Manjummel Boys Promo Song ",
      "url": "https://www.youtube.com/embed/9AizchSQURA",
      "date": "02/23/2024,7:35:08 PM"
    },
    {
      "id": "lt01tous",
      "cardname": "Kuthanthram - Manjummel Boys Promo Song ",
      "url": "https://www.youtube.com/embed/9AizchSQURA",
      "date": "02/24/2024,5:49:58 PM"
    },
    {
      "id": "lt034nsj",
      "cardname": "Kuthanthram - Manjummel Boys Promo Song ",
      "url": "https://www.youtube.com/embed/9AizchSQURA",
      "date": "02/24/2024,6:26:30 PM"
    },
    {
      "id": "lt034t0v",
      "cardname": "Alaye - Lyrical Video | Kasargold ",
      "url": "https://www.youtube.com/embed/aqAz_yXM5tg",
      "date": "02/24/2024,6:26:36 PM"
    },
    
    {
      "id": "lt4hh1jx",
      "cardname": "Alaye  - Lyrical Video  | Kasargold ",
      "url": "https://www.youtube.com/embed/aqAz_yXM5tg",
      "date": "02/27/2024,8:19:07 PM"
    },
    {
      "id": "luw6h5vk",
      "cardname": "Ingattu Nokku - Chattambi Promo Song ",
      "url": "https://www.youtube.com/embed/3QDZHzvUC_Q",
      "date": "04/12/2024,10:08:32 AM"
    },
    {
      "id": "luw6hc7d",
      "cardname": "Ingattu Nokku - Chattambi Promo Song ",
      "url": "https://www.youtube.com/embed/3QDZHzvUC_Q",
      "date": "04/12/2024,10:08:40 AM"
    },
    {
      "id": "luw6irzz",
      "cardname": "Ingattu Nokku - Chattambi Promo Song",
      "url": "https://www.youtube.com/embed/zfSkfgsKf5w",
      "date": "04/12/2024,10:09:47 AM"
    },
    {
      "id": "lw03vt3f",
      "cardname": "Illuminati|Aavesham|Jithu Madhavan|",
      "url": "https://www.youtube.com/embed/tOM-nWPcR4U",
      "date": "05/10/2024,8:46:43 AM"
    },
    {
      "id": "lw0ed5gj",
      "cardname": "React Tutorial for Beginners",
      "url": "https://www.youtube.com/embed/SqcY0GlETPk",
      "date": "05/10/2024,1:40:08 PM"
    }
  ]
}